{
"type": "FeatureCollection",
"crs": { "type": "name", "properties": { "name": "urn:ogc:def:crs:OGC:1.3:CRS84" } },
                                                                                
"features": [
{ "type": "Feature", "properties": { "id": null, "Nom": "Hopital bouffard" }, "geometry": { "type": "Point", "coordinates": [ 43.152980763068662, 11.587069142667207 ] } }
]
}
