{
"type": "FeatureCollection",
"name": "nouveau",
"crs": { "type": "name", "properties": { "name": "urn:ogc:def:crs:OGC:1.3:CRS84" } },
"features": [
{ "type": "Feature", "properties": { "id": null, "nom": "ALI OMAR ALI", "Quartier": "HODAN" }, "geometry": { "type": "Point", "coordinates": [ 43.096160548327155, 11.5558782527881 ] } },
{ "type": "Feature", "properties": { "id": null, "nom": "SAIDA SALAH ALI", "Quartier": "HAYABLEY" }, "geometry": { "type": "Point", "coordinates": [ 43.095812035316001, 11.570486756505572 ] } }
]
}
